pyueye/__init__.py
pyueye/dll.py
pyueye/ueye.py
pyueye/ueye_tools.py
senseye_pyueye-0.2.0.dist-info/METADATA
senseye_pyueye-0.2.0.dist-info/WHEEL
senseye_pyueye-0.2.0.dist-info/top_level.txt
senseye_pyueye-0.2.0.dist-info/RECORD
