Metadata-Version: 2.1
Name: senseye-pyueye
Version: 0.2.0
Summary: pyueye - Python bindings for uEye API.
Home-page: http://www.ids-imaging.com
Author: IDS Imaging Development Systems GmbH
Author-email: info@ids-imaging.com
License: 3-Clause BSD License
Platform: UNKNOWN
